[
  {
    "customerNm": 1,
    "houseNm": 2,
    "apartmentNm": 3,
    "counterState": 4,
    "counterType": "Wasser",
    "counterNum": 5,
    "date": "11.11.2000",
    "counterSwitch": false,
    "comment": "haren"
  },
  {
    "customerNm": 6,
    "houseNm": 5,
    "apartmentNm": 4,
    "counterState": 3,
    "counterType": "Wasser",
    "counterNum": 2,
    "date": "01.01.2000",
    "counterSwitch": false,
    "comment": "kelb"
  },
  {
    "customerNm": 1243,
    "houseNm": 4321,
    "apartmentNm": 4,
    "counterState": 213468987,
    "counterType": "Wasser",
    "counterNum": 56,
    "date": "31.12.2010",
    "counterSwitch": false,
    "comment": "Herr Kelb wechselt nicht"
  },
  {
    "customerNm": 3759336,
    "houseNm": 46,
    "apartmentNm": 2,
    "counterState": 123757483,
    "counterType": "Wasser",
    "counterNum": 129,
    "date": "30.06.2011",
    "counterSwitch": false,
    "comment": "Zählerstand steht noch da, aber in jahren wechseln"
  },
  {
    "customerNm": 1,
    "houseNm": 2,
    "apartmentNm": 3,
    "counterState": 4,
    "counterType": "Wasser",
    "counterNum": 5,
    "date": "01.01.2004",
    "counterSwitch": false,
    "comment": "Test"
  }
]